Metadata-Version: 2.1
Name: RuMyrevolver
Version: 0.0.2
Summary: It's just a Russian roll.
Home-page: http://info.cern.ch/hypertext/WWW/TheProject.html
Author: WhoDol
Classifier: Programming Language :: Python :: 3
Classifier: License :: OSI Approved :: MIT License
Classifier: Operating System :: OS Independent
